{
  "cacheBootResources": true,
  "debugBuild": false,
  "entryAssembly": "Blazorwasm",
  "linkerEnabled": true,
  "resources": {
    "assembly": {
      "Blazor.SignaturePad.dll": "sha256-fiGPXG7yNXvzDiMsM+JDU70ZTZ4ijgyUC+3CqswFmH0=",
      "Blazorwasm.dll": "sha256-wSQiBS0dv03NOHisuTzuE4XVLB300PtUSS4IRVT6tdY=",
      "Microsoft.AspNetCore.Blazor.HttpClient.dll": "sha256-myeuIF4ncrpEUKTNlx\/Ka5VHA3wkZ1NdvsLPJtA91TY=",
      "Microsoft.AspNetCore.Components.dll": "sha256-605plSOMPHCt4W0mDEnj9otJ+sm097DSxiEzK3Hm1c0=",
      "Microsoft.AspNetCore.Components.Web.dll": "sha256-oyIPyoKOs2g3ARqPBokZVqG7dFAlEfN0Bd5\/rSoC0VA=",
      "Microsoft.AspNetCore.Components.WebAssembly.dll": "sha256-fzRUrMuziqoqkbexKhIXJoUIjuDePWtkkIySgUz7zb8=",
      "Microsoft.Bcl.AsyncInterfaces.dll": "sha256-jzHgXWAvWMkKIGFjZoT84tbe72E+H7CvTr\/Dryh4QPs=",
      "Microsoft.Extensions.Configuration.Abstractions.dll": "sha256-0Kr2rjpUGprqGKDeUmIYqpppqnA9+nLry0myD5yfdKU=",
      "Microsoft.Extensions.Configuration.dll": "sha256-6dldRp3jnaIEgGoMk4m3xnNKUgoJaYBwVuMLFXWIBb0=",
      "Microsoft.Extensions.DependencyInjection.Abstractions.dll": "sha256-ikGrnBaOiZlWcHUL8seH18IN6FARvUMyfU4DO+Cc\/cc=",
      "Microsoft.Extensions.DependencyInjection.dll": "sha256-RFiVNcm3hJveG8Twjnlg\/BahQhI1fA48ZxVpe1qf8y0=",
      "Microsoft.Extensions.Logging.Abstractions.dll": "sha256-WFo6RRfH9HHgnQISSbcR6++G1xjVIqjSAjxJTt+RrGI=",
      "Microsoft.Extensions.Primitives.dll": "sha256-JZD1Rgl70n6QpSYwN+pYuCNI\/z1\/f9mcTkGk72yB\/qQ=",
      "Microsoft.JSInterop.dll": "sha256-CJ0jnf2G21cOvZYQt\/4NVkv642Xz8fLQyPnHvcfP3D4=",
      "Microsoft.JSInterop.WebAssembly.dll": "sha256-VP8179q6KlTFT\/O0r6zq3Il8a0P7HOsHY2h35s5Lpng=",
      "mscorlib.dll": "sha256-EeaFbOt8mzlTZ1WLuuBVsOZJYObzaJzWfzAft\/ERDcg=",
      "System.Core.dll": "sha256-WvrNj8G3Mcp9vTc2fGGEhO\/iF+rfACKdcXQgrn5+hCc=",
      "System.dll": "sha256-CCi\/PbaK6j7QvaNb0l9o37a3dnnHl\/65JQLrr0yHR+k=",
      "System.Net.Http.dll": "sha256-s6oeOqweXMbAaAnmwQKvU9HMXTP0+TzS0SN8uTn1+Zs=",
      "System.Runtime.CompilerServices.Unsafe.dll": "sha256-JEjhcie\/wsk9l7jn+8UPQ\/noMW2TWZQZytf+VOcu5wo=",
      "System.Text.Encodings.Web.dll": "sha256-Ah8GCMFX+zka2Zh+\/SX5vFpsPse1IbVuosCVag4ojvw=",
      "System.Text.Json.dll": "sha256-rvsrPyA0WRGw667whVfD+jzfrusoYrTRD0V5a\/6s4RM=",
      "WebAssembly.Bindings.dll": "sha256-WZfMaUL65Y1FhhBqRPfvklVq82KmxVX2+WCD+NhDPNo=",
      "WebAssembly.Net.Http.dll": "sha256-zjrEeSlRs8Nznp0igYPUl3N\/klmwU4m4Lp7oRkiK284="
    },
    "runtime": {
      "dotnet.3.2.0-preview2.20159.2.js": "sha256-80Q7rIpqLxXzuMWqtC+FCBNrG15kR\/r+ba08n2TpQO0=",
      "dotnet.wasm": "sha256-TwiabWTQ0R8CJeRzc59eU16DKfcf2p8PIvZsyWF7\/8M="
    }
  }
}